[
  {
    "id": "1",
    "date": "16, FEB",
    "startTime": "06.30",
    "endTime": "08.45",
    "fromCountry": "Albania",
    "toCountry": "Algeria",
    "price": "125",
    "planeId": 1
  },
  {
    "id": "2",
    "date": "16, FEB",
    "startTime": "13.35",
    "endTime": "15.50",
    "fromCountry": "Albania",
    "toCountry": "Algeria",
    "price": "150",
    "planeId": 2
  },
  {
    "id": "3",
    "date": "16, FEB",
    "startTime": "16.40",
    "endTime": "18.55",
    "fromCountry": "Albania",
    "toCountry": "Algeria",
    "price": "115",
    "planeId": 3
  }
]